four_relay/SimpleIO.py
four_relay/WebConfig.py
four_relay/__init__.py
four_relay/boot.py
four_relay/main.py
four_relay/simple_relay.py
four_relay/switch_button.py
four_relay/webrepl_cfg.py
four_relay-0.1.2.dist-info/METADATA
four_relay-0.1.2.dist-info/RECORD
four_relay-0.1.2.dist-info/WHEEL
four_relay-0.1.2.dist-info/top_level.txt
four_relay_control_for_micropython/SimpleIO.py
four_relay_control_for_micropython/WebConfig.py
four_relay_control_for_micropython/__init__.py
four_relay_control_for_micropython/boot.py
four_relay_control_for_micropython/main.py
four_relay_control_for_micropython/simple_relay.py
four_relay_control_for_micropython/switch_button.py
four_relay_control_for_micropython/webrepl_cfg.py
four_relay_for_micropython/SimpleIO.py
four_relay_for_micropython/WebConfig.py
four_relay_for_micropython/__init__.py
four_relay_for_micropython/boot.py
four_relay_for_micropython/main.py
four_relay_for_micropython/simple_relay.py
four_relay_for_micropython/switch_button.py
four_relay_for_micropython/webrepl_cfg.py
