Metadata-Version: 2.1
Name: four-relay
Version: 0.1.2
Summary: Four relay control for micropython
Home-page: https://www.hachina.io
Author: HAchina
Author-email: 648993779@qq.com
License: UNKNOWN
Platform: UNKNOWN
Classifier: Programming Language :: Python :: 3
Classifier: License :: OSI Approved :: MIT License
Classifier: Operating System :: OS Independent
